aisim/__init__.py
aisim/atoms.py
aisim/beam.py
aisim/convert.py
aisim/det.py
aisim/dist.py
aisim/prop.py
aisim/zern.py
aisim-5.0.0.dist-info/LICENSE
aisim-5.0.0.dist-info/METADATA
aisim-5.0.0.dist-info/WHEEL
aisim-5.0.0.dist-info/top_level.txt
aisim-5.0.0.dist-info/RECORD
