Metadata-Version: 2.2
Name: aisim
Version: 5.0.0
Summary: Simulations for light-pulse atom interferometry
Author: Bastian Leykauf
Author-email: leykauf@physik.hu-berlin.de
License:                     GNU GENERAL PUBLIC LICENSE
Project-URL: homepage, https://github.com/bleykauf/aisim/
Project-URL: repository, https://github.com/bleykauf/aisim/
Classifier: Programming Language :: Python :: 3
Classifier: License :: OSI Approved :: GNU General Public License v3 (GPLv3)
Classifier: Operating System :: OS Independent
Classifier: Intended Audience :: Science/Research
Requires-Python: >=3.11
License-File: LICENSE
Requires-Dist: numpy<3.0.0,>=1.26.4
Requires-Dist: scipy<2.0,>=1.15.1
Requires-Dist: matplotlib<4.0.0,>=3.9.4
Provides-Extra: dev
Requires-Dist: ruff>=0.9.10; extra == "dev"
Requires-Dist: pre-commit>=4.1.0; extra == "dev"
Requires-Dist: pytest>=8.3.4; extra == "dev"
Requires-Dist: setuptools_scm>=8.1.0; extra == "dev"
Provides-Extra: docs
Requires-Dist: sphinx>=8.2.1; extra == "docs"
Requires-Dist: nbsphinx>=0.9.6; extra == "docs"
Requires-Dist: pygments>=2.4; extra == "docs"
Requires-Dist: sphinx_rtd_theme>=3.0.2; extra == "docs"
